db_fds/fdfuncs.py
db_fds-0.3.1.dist-info/licenses/LICENSE
db_fds-0.3.1.dist-info/METADATA
db_fds-0.3.1.dist-info/WHEEL
db_fds-0.3.1.dist-info/top_level.txt
db_fds-0.3.1.dist-info/RECORD
